CHANGES.md
CLASSIFIERS.md
ENTRY_POINTS.ini
LICENSE.md
MANIFEST.in
README.md
development.ini
setup.cfg
setup.py
flatpages/__init__.py
flatpages/extensibility.py
flatpages/interfaces.py
flatpages/resources.py
flatpages/routes.py
flatpages/views.py
flatpages/wsgi.py
flatpages/data_sources/__init__.py
flatpages/data_sources/git.py
flatpages/data_sources/shortcuts.py
flatpages/renderers/__init__.py
flatpages/renderers/defaults.py
flatpages/renderers/markdown.py
flatpages/util/__init__.py
flatpages/util/pages.py
pyramid_flatpages.egg-info/PKG-INFO
pyramid_flatpages.egg-info/SOURCES.txt
pyramid_flatpages.egg-info/dependency_links.txt
pyramid_flatpages.egg-info/entry_points.txt
pyramid_flatpages.egg-info/not-zip-safe
pyramid_flatpages.egg-info/requires.txt
pyramid_flatpages.egg-info/top_level.txt