Metadata-Version: 1.0
Name: pyramid-flatpages
Version: 0.0.1-mdfix
Summary: Manage your site's pages using configurable data sources for storage.
Home-page: http://github.com/LimpidTech/pyramid-flatpages/
Author: Brandon R. Stoner
Author-email: monokrome@limpidtech.com
License: UNKNOWN
Keywords: web pylons pyramid
Platform: UNKNOWN
